dm_mcp_server.py
dm_mcp_server-2.2.0.dist-info/licenses/LICENSE
dm_mcp_server-2.2.0.dist-info/METADATA
dm_mcp_server-2.2.0.dist-info/WHEEL
dm_mcp_server-2.2.0.dist-info/entry_points.txt
dm_mcp_server-2.2.0.dist-info/top_level.txt
dm_mcp_server-2.2.0.dist-info/RECORD
