Metadata-Version: 2.4
Name: dm-mcp-server
Version: 2.2.0
Summary: 达梦数据库 Model Context Protocol (MCP) 服务器
Home-page: https://github.com/CleanCodeStar/dm_mcp_server
Author: CleanCode
Author-email: AI Assistant <ai@example.com>
Maintainer-email: AI Assistant <ai@example.com>
License-Expression: MIT
Project-URL: Homepage, https://github.com/your-username/dm-mcp-server
Project-URL: Documentation, https://github.com/your-username/dm-mcp-server#readme
Project-URL: Repository, https://github.com/your-username/dm-mcp-server.git
Project-URL: Bug Tracker, https://github.com/your-username/dm-mcp-server/issues
Keywords: dameng,database,mcp,model-context-protocol,dmPython
Classifier: Development Status :: 5 - Production/Stable
Classifier: Intended Audience :: Developers
Classifier: Topic :: Database
Classifier: Topic :: Software Development :: Libraries :: Python Modules
Classifier: Programming Language :: Python :: 3
Classifier: Programming Language :: Python :: 3.8
Classifier: Programming Language :: Python :: 3.9
Classifier: Programming Language :: Python :: 3.10
Classifier: Programming Language :: Python :: 3.11
Classifier: Programming Language :: Python :: 3.12
Classifier: Operating System :: OS Independent
Requires-Python: >=3.8
License-File: LICENSE
Requires-Dist: mcp>=1.0.0
Requires-Dist: dmPython>=2.0.0
Dynamic: author
Dynamic: home-page
Dynamic: license-file
Dynamic: requires-python
